pyleco/__init__.py
pyleco/errors.py
pyleco/test.py
pyleco/actors/__init__.py
pyleco/actors/actor.py
pyleco/actors/locking_actor.py
pyleco/coordinators/__init__.py
pyleco/coordinators/coordinator.py
pyleco/coordinators/proxy_server.py
pyleco/core/__init__.py
pyleco/core/data_message.py
pyleco/core/internal_protocols.py
pyleco/core/leco_protocols.py
pyleco/core/message.py
pyleco/core/serialization.py
pyleco/directors/__init__.py
pyleco/directors/coordinator_director.py
pyleco/directors/data_logger_director.py
pyleco/directors/director.py
pyleco/directors/locking_director.py
pyleco/directors/starter_director.py
pyleco/directors/transparent_director.py
pyleco/json_utils/__init__.py
pyleco/json_utils/errors.py
pyleco/json_utils/json_objects.py
pyleco/json_utils/json_parser.py
pyleco/json_utils/rpc_generator.py
pyleco/json_utils/rpc_server.py
pyleco/management/__init__.py
pyleco/management/data_logger.py
pyleco/management/starter.py
pyleco/management/test_tasks/failing_task.py
pyleco/management/test_tasks/no_task.py
pyleco/management/test_tasks/test_task.py
pyleco/utils/__init__.py
pyleco/utils/base_communicator.py
pyleco/utils/communicator.py
pyleco/utils/coordinator_utils.py
pyleco/utils/data_publisher.py
pyleco/utils/events.py
pyleco/utils/extended_message_handler.py
pyleco/utils/listener.py
pyleco/utils/log_levels.py
pyleco/utils/message_handler.py
pyleco/utils/message_handler_base.py
pyleco/utils/parser.py
pyleco/utils/pipe_handler.py
pyleco/utils/qt_listener.py
pyleco/utils/rpc_handler.py
pyleco/utils/timers.py
pyleco/utils/zmq_log_handler.py
pyleco-0.6.0.post1.dist-info/licenses/AUTHORS.txt
pyleco-0.6.0.post1.dist-info/licenses/LICENSE
pyleco-0.6.0.post1.dist-info/METADATA
pyleco-0.6.0.post1.dist-info/WHEEL
pyleco-0.6.0.post1.dist-info/entry_points.txt
pyleco-0.6.0.post1.dist-info/top_level.txt
pyleco-0.6.0.post1.dist-info/RECORD
