Metadata-Version: 2.4
Name: pyleco
Version: 0.6.0.post1
Summary: Python reference implementation of the Laboratory Experiment COntrol (LECO) protocol
Author: PyLECO Developers
License: MIT License
Project-URL: Homepage, https://github.com/pymeasure/pyleco
Project-URL: Bug Tracker, https://github.com/pymeasure/pyleco/issues
Classifier: Programming Language :: Python :: 3
Classifier: Programming Language :: Python :: 3.8
Classifier: Programming Language :: Python :: 3.9
Classifier: Programming Language :: Python :: 3.10
Classifier: Programming Language :: Python :: 3.11
Classifier: Programming Language :: Python :: 3.12
Classifier: Programming Language :: Python :: 3.13
Classifier: Development Status :: 4 - Beta
Classifier: License :: OSI Approved :: MIT License
Classifier: Operating System :: OS Independent
Classifier: Intended Audience :: Science/Research
Classifier: Topic :: Scientific/Engineering
Classifier: Topic :: System :: Networking
Requires-Python: >=3.8
License-File: LICENSE
License-File: AUTHORS.txt
Requires-Dist: pyzmq>=22.3.0
Requires-Dist: uuid6>=2024.1.12
Provides-Extra: dev
Requires-Dist: pytest; extra == "dev"
Requires-Dist: pytest-cov; extra == "dev"
Requires-Dist: sphinx; extra == "dev"
Requires-Dist: sphinx_rtd_theme; extra == "dev"
Dynamic: license-file
